(*
  Copyright 2017 Luca Boasso. All rights reserved.
  Use of this source code is governed by a MIT
  license that can be found in the LICENSE file.
*)

MODULE Opcodes;
  CONST 
    (* access flags *)
    ACCxPUBLIC* = 0001H;
    ACCxPRIVATE* = 0002H;
    ACCxPROTECTED* = 0004H;
    ACCxSTATIC* = 0008H;
    ACCxFINAL* = 0010H;
    ACCxSUPER* = 0020H;
    ACCxSYNCHRONIZED* = 0020H;
    ACCxVOLATILE* = 0040H;
    ACCxBRIDGE* = 0040H;
    ACCxVARARGS* = 0080H;
    ACCxTRANSIENT* = 0080H;
    ACCxNATIVE* = 0100H;
    ACCxINTERFACE* = 0200H;
    ACCxABSTRACT* = 0400H;
    ACCxSTRICT* = 0800H;
    ACCxSYNTHETIC* = 1000H;
    ACCxANNOTATION* = 2000H;
    ACCxENUM* = 4000H;
    ACCxMANDATED* = 8000H;

    (* types for NEWARRAY *)
    TBOOLEAN* = 4;
    TCHAR* = 5;
    TFLOAT* = 6;
    TDOUBLE* = 7;
    TBYTE* = 8;
    TSHORT* = 9;
    TINT* = 10;
    TLONG* = 11;

    (* opcodes *)
    NOP* = 0;
    ACONSTNULL* = 1;
    ICONSTM1* = 2;
    ICONST0* = 3;
    ICONST1* = 4;
    ICONST2* = 5;
    ICONST3* = 6;
    ICONST4* = 7;
    ICONST5* = 8;
    LCONST0* = 9;
    LCONST1* = 10;
    FCONST0* = 11;
    FCONST1* = 12;
    FCONST2* = 13;
    DCONST0* = 14;
    DCONST1* = 15;
    BIPUSH* = 16;
    SIPUSH* = 17;
    LDC* = 18;
    LDCW* = 19;
    LDC2W* = 20;
    ILOAD* = 21;
    LLOAD* = 22;
    FLOAD* = 23;
    DLOAD* = 24;
    ALOAD* = 25;
    ILOAD0* = 26;
    ILOAD1* = 27;
    ILOAD2* = 28;
    ILOAD3* = 29;
    LLOAD0* = 30;
    LLOAD1* = 31;
    LLOAD2* = 32;
    LLOAD3* = 33;
    FLOAD0* = 34;
    FLOAD1* = 35;
    FLOAD2* = 36;
    FLOAD3* = 37;
    DLOAD0* = 38;
    DLOAD1* = 39;
    DLOAD2* = 40;
    DLOAD3* = 41;
    ALOAD0* = 42;
    ALOAD1* = 43;
    ALOAD2* = 44;
    ALOAD3* = 45;
    IALOAD* = 46;
    LALOAD* = 47;
    FALOAD* = 48;
    DALOAD* = 49;
    AALOAD* = 50;
    BALOAD* = 51;
    CALOAD* = 52;
    SALOAD* = 53;
    ISTORE* = 54;
    LSTORE* = 55;
    FSTORE* = 56;
    DSTORE* = 57;
    ASTORE* = 58;
    ISTORE0* = 59;
    ISTORE1* = 60;
    ISTORE2* = 61;
    ISTORE3* = 62;
    LSTORE0* = 63;
    LSTORE1* = 64;
    LSTORE2* = 65;
    LSTORE3* = 66;
    FSTORE0* = 67;
    FSTORE1* = 68;
    FSTORE2* = 69;
    FSTORE3* = 70;
    DSTORE0* = 71;
    DSTORE1* = 72;
    DSTORE2* = 73;
    DSTORE3* = 74;
    ASTORE0* = 75;
    ASTORE1* = 76;
    ASTORE2* = 77;
    ASTORE3* = 78;
    IASTORE* = 79;
    LASTORE* = 80;
    FASTORE* = 81;
    DASTORE* = 82;
    AASTORE* = 83;
    BASTORE* = 84;
    CASTORE* = 85;
    SASTORE* = 86;
    POP* = 87;
    POP2* = 88;
    DUP* = 89;
    DUPX1* = 90;
    DUPX2* = 91;
    DUP2* = 92;
    DUP2X1* = 93;
    DUP2X2* = 94;
    SWAP* = 95;
    IADD* = 96;
    LADD* = 97;
    FADD* = 98;
    DADD* = 99;
    ISUB* = 100;
    LSUB* = 101;
    FSUB* = 102;
    DSUB* = 103;
    IMUL* = 104;
    LMUL* = 105;
    FMUL* = 106;
    DMUL* = 107;
    IDIV* = 108;
    LDIV* = 109;
    FDIV* = 110;
    DDIV* = 111;
    IREM* = 112;
    LREM* = 113;
    FREM* = 114;
    DREM* = 115;
    INEG* = 116;
    LNEG* = 117;
    FNEG* = 118;
    DNEG* = 119;
    ISHL* = 120;
    LSHL* = 121;
    ISHR* = 122;
    LSHR* = 123;
    IUSHR* = 124;
    LUSHR* = 125;
    IAND* = 126;
    LAND* = 127;
    IOR* = 128;
    LOR* = 129;
    IXOR* = 130;
    LXOR* = 131;
    IINC* = 132;
    I2L* = 133;
    I2F* = 134;
    I2D* = 135;
    L2I* = 136;
    L2F* = 137;
    L2D* = 138;
    F2I* = 139;
    F2L* = 140;
    F2D* = 141;
    D2I* = 142;
    D2L* = 143;
    D2F* = 144;
    I2B* = 145;
    I2C* = 146;
    I2S* = 147;
    LCMP* = 148;
    FCMPL* = 149;
    FCMPG* = 150;
    DCMPL* = 151;
    DCMPG* = 152;
    IFEQ* = 153;
    IFNE* = 154;
    IFLT* = 155;
    IFGE* = 156;
    IFGT* = 157;
    IFLE* = 158;
    IFICMPEQ* = 159;
    IFICMPNE* = 160;
    IFICMPLT* = 161;
    IFICMPGE* = 162;
    IFICMPGT* = 163;
    IFICMPLE* = 164;
    IFACMPEQ* = 165;
    IFACMPNE* = 166;
    GOTO* = 167;
    JSR* = 168;
    RET* = 169;
    TABLESWITCH* = 170;
    LOOKUPSWITCH* = 171;
    IRETURN* = 172;
    LRETURN* = 173;
    FRETURN* = 174;
    DRETURN* = 175;
    ARETURN* = 176;
    RETURNx* = 177;
    GETSTATIC* = 178;
    PUTSTATIC* = 179;
    GETFIELD* = 180;
    PUTFIELD* = 181;
    INVOKEVIRTUAL* = 182;
    INVOKESPECIAL* = 183;
    INVOKESTATIC* = 184;
    INVOKEINTERFACE* = 185;
    INVOKEDYNAMIC* = 186;
    NEW* = 187;
    NEWARRAY* = 188;
    ANEWARRAY* = 189;
    ARRAYLENGTH* = 190;
    ATHROW* = 191;
    CHECKCAST* = 192;
    INSTANCEOF* = 193;
    MONITORENTER* = 194;
    MONITOREXIT* = 195;
    WIDE* = 196;
    MULTIANEWARRAY* = 197;
    IFNULL* = 198;
    IFNONNULL* = 199;
    GOTOW* = 200;
    JSRW* = 201;
END Opcodes.
